constant_nums/__init__.py
constant_nums/final.py
constant_nums-0.5.dist-info/METADATA
constant_nums-0.5.dist-info/WHEEL
constant_nums-0.5.dist-info/top_level.txt
constant_nums-0.5.dist-info/RECORD
