Metadata-Version: 2.1
Name: constant-nums
Version: 0.5
Summary: Konstant
Home-page: UNKNOWN
Author: Ashutosh Joshi
License: UNKNOWN
Platform: UNKNOWN
